vivian/__init__.py
vivian/__version__.py
vivian/cli.py
vivian/vivian.py
vivian-0.0.1.dev11.dist-info/LICENSE
vivian-0.0.1.dev11.dist-info/METADATA
vivian-0.0.1.dev11.dist-info/WHEEL
vivian-0.0.1.dev11.dist-info/entry_points.txt
vivian-0.0.1.dev11.dist-info/top_level.txt
vivian-0.0.1.dev11.dist-info/RECORD
