Metadata-Version: 2.1
Name: vivian
Version: 0.0.1.dev11
Summary: vivian is a multi-process CLI tool for URLs redirection veirfication by loading cases from a csv file. It's easy to integrated with pipeline for smoking or regression test.
Home-page: https://github.com/wizardbyron/vivian
Author: wizardbyron
Author-email: wizard0530@gmail.com
License: UNKNOWN
Keywords: url,redirection,redirect,verify,test,tests
Platform: UNKNOWN
Classifier: Programming Language :: Python
Classifier: Programming Language :: Python :: 3
Classifier: Development Status :: 3 - Alpha
Classifier: Environment :: Console
Classifier: Intended Audience :: Developers
Classifier: Intended Audience :: System Administrators
Classifier: License :: OSI Approved :: MIT License
Classifier: Operating System :: MacOS
Classifier: Operating System :: POSIX :: Linux
Classifier: Topic :: Internet :: WWW/HTTP
Classifier: Topic :: Internet :: WWW/HTTP :: HTTP Servers
Classifier: Topic :: Internet :: WWW/HTTP :: Site Management
Classifier: Topic :: Internet :: WWW/HTTP :: Site Management :: Link Checking
Classifier: Topic :: Software Development :: Testing
Classifier: Topic :: Utilities
Requires-Python: >=2.6, !=3.0.*, !=3.1.*, !=3.2.*, <4
Requires-Dist: requests
